setup.py
rubick_estimator_server/__init__.py
rubick_estimator_server/base.py
rubick_estimator_server.egg-info/PKG-INFO
rubick_estimator_server.egg-info/SOURCES.txt
rubick_estimator_server.egg-info/dependency_links.txt
rubick_estimator_server.egg-info/requires.txt
rubick_estimator_server.egg-info/top_level.txt