Metadata-Version: 1.0
Name: rubick-estimator-server
Version: 0.0.2
Summary: Draw pic with amap js api
Home-page: http://xlvecle.github.io/rubick
Author: xlvecle
Author-email: xlvecle@xlvecle.com
License:             DO WHAT THE FUCK YOU WANT TO PUBLIC LICENSE
